README.rst
setup.cfg
setup.py
TracPortalPlugin.egg-info/PKG-INFO
TracPortalPlugin.egg-info/SOURCES.txt
TracPortalPlugin.egg-info/dependency_links.txt
TracPortalPlugin.egg-info/entry_points.txt
TracPortalPlugin.egg-info/requires.txt
TracPortalPlugin.egg-info/top_level.txt
TracPortalPlugin.egg-info/zip-safe
tracportal/__init__.py
tracportal/api.py
tracportal/core.py
tracportal/i18n.py
tracportal/upgrade.py
tracportal/util.py
tracportal/dashboard/__init__.py
tracportal/dashboard/web_api.py
tracportal/dashboard/web_ui.py
tracportal/dashboard/templates/dashboard.html
tracportal/htdocs/indicator.gif
tracportal/htdocs/loader.gif
tracportal/htdocs/settings.png
tracportal/htdocs/update.png
tracportal/htdocs/css/cross_search.css
tracportal/htdocs/css/dashboard.css
tracportal/htdocs/css/new_project.css
tracportal/htdocs/css/project_list.css
tracportal/htdocs/css/smoothness/jquery-ui-1.10.3.custom.min.css
tracportal/htdocs/css/smoothness/images/animated-overlay.gif
tracportal/htdocs/css/smoothness/images/ui-bg_flat_0_aaaaaa_40x100.png
tracportal/htdocs/css/smoothness/images/ui-bg_flat_75_ffffff_40x100.png
tracportal/htdocs/css/smoothness/images/ui-bg_glass_55_fbf9ee_1x400.png
tracportal/htdocs/css/smoothness/images/ui-bg_glass_65_ffffff_1x400.png
tracportal/htdocs/css/smoothness/images/ui-bg_glass_75_dadada_1x400.png
tracportal/htdocs/css/smoothness/images/ui-bg_glass_75_e6e6e6_1x400.png
tracportal/htdocs/css/smoothness/images/ui-bg_glass_95_fef1ec_1x400.png
tracportal/htdocs/css/smoothness/images/ui-bg_highlight-soft_75_cccccc_1x100.png
tracportal/htdocs/css/smoothness/images/ui-icons_222222_256x240.png
tracportal/htdocs/css/smoothness/images/ui-icons_2e83ff_256x240.png
tracportal/htdocs/css/smoothness/images/ui-icons_454545_256x240.png
tracportal/htdocs/css/smoothness/images/ui-icons_888888_256x240.png
tracportal/htdocs/css/smoothness/images/ui-icons_cd0a0a_256x240.png
tracportal/htdocs/js/cross_search.js
tracportal/htdocs/js/dashboard.js
tracportal/htdocs/js/jquery-1.9.1.js
tracportal/htdocs/js/jquery-ui-1.10.3.custom.min.js
tracportal/htdocs/js/jquery.compat-1.0.js
tracportal/htdocs/js/project_list.js
tracportal/htdocs/js/messages/ja.js
tracportal/locale/messages-js.pot
tracportal/locale/messages.pot
