Metadata-Version: 1.0
Name: TracPortalPlugin
Version: 0.2
Summary: Provide trac portal pages for multiple projects.
Home-page: https://github.com/iij/TracPortalPlugin
Author: yosinobu
Author-email: yosinobu@iij.ad.jp
License: MIT
Platform: UNKNOWN
